odoo10_addon_web_drop_target-10.0.1.0.1-py2.7-nspkg.pth
odoo/addons/web_drop_target/README.rst
odoo/addons/web_drop_target/__init__.py
odoo/addons/web_drop_target/__manifest__.py
odoo/addons/web_drop_target/i18n/web_drop_target.pot
odoo/addons/web_drop_target/static/description/icon.png
odoo/addons/web_drop_target/static/lib/base64js.min.js
odoo/addons/web_drop_target/static/src/css/web_drop_target.css
odoo/addons/web_drop_target/static/src/js/web_drop_target.js
odoo/addons/web_drop_target/views/templates.xml
odoo10_addon_web_drop_target-10.0.1.0.1.dist-info/METADATA
odoo10_addon_web_drop_target-10.0.1.0.1.dist-info/RECORD
odoo10_addon_web_drop_target-10.0.1.0.1.dist-info/WHEEL
odoo10_addon_web_drop_target-10.0.1.0.1.dist-info/namespace_packages.txt
odoo10_addon_web_drop_target-10.0.1.0.1.dist-info/top_level.txt
